gselogger/__init__.py
gselogger/_version.py
gselogger/logger_model.py
GSELogger-1.0.1.dist-info/LICENSE
GSELogger-1.0.1.dist-info/METADATA
GSELogger-1.0.1.dist-info/WHEEL
GSELogger-1.0.1.dist-info/top_level.txt
GSELogger-1.0.1.dist-info/RECORD
