Metadata-Version: 2.1
Name: GSELogger
Version: 1.0.1
Summary: Python logging model for any python application.
Home-page: https://github.com/GSECARS/GSELogger
Author: Christofanis Skordas
Author-email: skordasc@uchicago.edu
Project-URL: Bug Tracker, https://github.com/GSECARS/GSELogger/issues
Classifier: Intended Audience :: Science/Research
Classifier: Operating System :: OS Independent
Classifier: Programming Language :: Python :: 3
Classifier: Programming Language :: Python :: 3 :: Only
Classifier: Programming Language :: Python :: 3.10
Classifier: License :: OSI Approved :: GNU General Public License v3 (GPLv3)
Classifier: Topic :: Scientific/Engineering
Requires-Python: >=3.10
License-File: LICENSE
Provides-Extra: testing
Requires-Dist: versioneer (>=0.28) ; extra == 'testing'
Requires-Dist: flake8 (>=6.0.0) ; extra == 'testing'
Requires-Dist: mypy (>=1.0.1) ; extra == 'testing'
Requires-Dist: pytest (>=7.2.1) ; extra == 'testing'
Requires-Dist: pytest-cov (>=4.0.0) ; extra == 'testing'
Requires-Dist: tox (>=4.4.6) ; extra == 'testing'
